cypherpunkpay/__init__.py
cypherpunkpay/app.py
cypherpunkpay/bitcoin/__init__.py
cypherpunkpay/bitcoin/bip32.py
cypherpunkpay/bitcoin/electrum/LICENSE
cypherpunkpay/bitcoin/electrum/README
cypherpunkpay/bitcoin/electrum/__init__.py
cypherpunkpay/bitcoin/electrum/bip32.py
cypherpunkpay/bitcoin/electrum/bitcoin.py
cypherpunkpay/bitcoin/electrum/constants.py
cypherpunkpay/bitcoin/electrum/crypto.py
cypherpunkpay/bitcoin/electrum/ecc.py
cypherpunkpay/bitcoin/electrum/lnaddr.py
cypherpunkpay/bitcoin/electrum/msqr.py
cypherpunkpay/bitcoin/electrum/util.py
cypherpunkpay/bitcoin/helpers.py
cypherpunkpay/bitcoin/ln_invoice.py
cypherpunkpay/bitcoin/pwuille/__init__.py
cypherpunkpay/bitcoin/pwuille/segwit_addr.py
cypherpunkpay/common.py
cypherpunkpay/config/__init__.py
cypherpunkpay/config/config.py
cypherpunkpay/config/config_parser.py
cypherpunkpay/config/cypherpunkpay_defaults.conf
cypherpunkpay/config/cypherpunkpay_dev.conf
cypherpunkpay/config/cypherpunkpay_test.conf
cypherpunkpay/config/development.ini
cypherpunkpay/config/production.ini
cypherpunkpay/config/test.ini
cypherpunkpay/cypherpunkpay.py
cypherpunkpay/db/__init__.py
cypherpunkpay/db/db.py
cypherpunkpay/db/dev_examples.py
cypherpunkpay/db/migrations/20200805_01_xWgrN-create-globals.py
cypherpunkpay/db/migrations/20200805_02_DOy78-create-users.py
cypherpunkpay/db/migrations/20200805_03_aTTwI-create-charges.py
cypherpunkpay/db/migrations/20200805_04_hdebK-create-dummy-store-orders.py
cypherpunkpay/db/migrations/20210614_05_x4EMp-create-coins.py
cypherpunkpay/db/migrations/20210629_01_W6beI-add-column-charges-cc-lightning-payment-request.py
cypherpunkpay/db/migrations/20211227_01_uF3tk-add-columns-charges-beneficiary-what-for.py
cypherpunkpay/db/migrations/20211231_01_xw0BB-rename-column-charges-payment-completed-url-called-at.py
cypherpunkpay/db/migrations/__init__.py
cypherpunkpay/db/sqlite_db.py
cypherpunkpay/db/sqlite_type_assertions.py
cypherpunkpay/exceptions.py
cypherpunkpay/explorers/__init__.py
cypherpunkpay-1.0.11.dist-info/entry_points.txt
cypherpunkpay-1.0.11.dist-info/LICENSE
cypherpunkpay-1.0.11.dist-info/WHEEL
cypherpunkpay-1.0.11.dist-info/METADATA
cypherpunkpay-1.0.11.dist-info/RECORD
